mkdocs_remove_sections_plugin/__init__.py
mkdocs_remove_sections_plugin-0.1.0.dist-info/LICENSE
mkdocs_remove_sections_plugin-0.1.0.dist-info/METADATA
mkdocs_remove_sections_plugin-0.1.0.dist-info/WHEEL
mkdocs_remove_sections_plugin-0.1.0.dist-info/entry_points.txt
mkdocs_remove_sections_plugin-0.1.0.dist-info/top_level.txt
mkdocs_remove_sections_plugin-0.1.0.dist-info/RECORD
